osmrdf2023/__init__.py
osmrdf2023/osmrdf2023.py
osmrdf2023-0.4.1.dist-info/LICENSE
osmrdf2023-0.4.1.dist-info/METADATA
osmrdf2023-0.4.1.dist-info/WHEEL
osmrdf2023-0.4.1.dist-info/top_level.txt
osmrdf2023-0.4.1.dist-info/RECORD
